test.py
test/__init__.py
test/test_logs.py
wkregister/__init__.py
wkregister/decorator.py
wkregister/models.py
wkregister/producer.py
wkregister/util.py
wkregister-0.0.8.dist-info/LICENSE
wkregister-0.0.8.dist-info/METADATA
wkregister-0.0.8.dist-info/WHEEL
wkregister-0.0.8.dist-info/top_level.txt
wkregister-0.0.8.dist-info/RECORD
