Metadata-Version: 2.1
Name: wkregister
Version: 0.0.8
Summary: A wk register library for python
Author-email: Gustavo <gustavo.gordillo.giron@gmail.com>
Project-URL: Homepage, https://github.com/gtavo95/wknmi.git
Classifier: Programming Language :: Python :: 3
Classifier: License :: OSI Approved :: MIT License
Classifier: Operating System :: OS Independent
Requires-Python: >=3.8
License-File: LICENSE
Requires-Dist: confluent-kafka
